{
    "code":200,
    "data":{
        "sddl":{
            "A":0,
            "B":20,
            "C":0
        },
        "sdjk":{
            "A":0,
            "B":20,
            "C":0
        },
        "pddl":{
            "A":0,
            "B":30,
            "C":0
        },
        "pdjk":{
            "A":10,
            "B":0,
            "C":0
        },
        "zbyh":{
            "A":10,
            "B":0,
            "C":0
        },
        "bdz":{
            "A":10,
            "B":0,
            "C":0
        },
        "kbs":{
            "A":0,
            "B":20,
            "C":0
        },
        "hwg":{
            "A":0,
            "B":0,
            "C":30
        }
    },
    "status":"success"
}